{
  "sector_mapping": {
    "Technology": 0,
    "Healthcare": 1,
    "Financial Services": 2,
    "Energy": 3,
    "Consumer Cyclical": 4,
    "Industrials": 5,
    "Communication Services": 6,
    "Consumer Defensive": 7,
    "Real Estate": 8,
    "Utilities": 9,
    "Unknown": 10
  },
  "industry_mapping": {
    "Software\u2014Application": 0,
    "Software\u2014Infrastructure": 1,
    "Semiconductors": 2,
    "Computer Hardware": 3,
    "Consumer Electronics": 4,
    "Internet Content & Information": 5,
    "Electronic Gaming & Multimedia": 6,
    "Information Technology Services": 7,
    "Scientific & Technical Instruments": 8,
    "Solar": 9,
    "Drug Manufacturers\u2014General": 10,
    "Drug Manufacturers\u2014Specialty & Generic": 11,
    "Biotechnology": 12,
    "Medical Devices": 13,
    "Healthcare Plans": 14,
    "Banks\u2014Diversified": 15,
    "Banks\u2014Regional": 16,
    "Insurance\u2014Life": 17,
    "Insurance\u2014Property & Casualty": 18,
    "Asset Management": 19,
    "Oil & Gas Integrated": 20,
    "Oil & Gas E&P": 21,
    "Oil & Gas Refining & Marketing": 22,
    "Oil & Gas Midstream": 23,
    "Renewable Energy": 24,
    "Auto Manufacturers": 25,
    "Auto Parts": 26,
    "Restaurants": 27,
    "Specialty Retail": 28,
    "Internet Retail": 29,
    "Aerospace & Defense": 30,
    "Industrial Machinery": 31,
    "Building Materials": 32,
    "Transportation & Logistics": 33,
    "Electrical Equipment & Parts": 34,
    "Telecom Services": 35,
    "Entertainment": 36,
    "Interactive Media & Services": 37,
    "Broadcasting": 38,
    "Advertising Agencies": 39,
    "Beverages\u2014Non-Alcoholic": 40,
    "Food Distribution": 41,
    "Packaged Foods": 42,
    "Household & Personal Products": 43,
    "Discount Stores": 44,
    "REIT\u2014Retail": 45,
    "REIT\u2014Residential": 46,
    "REIT\u2014Industrial": 47,
    "Utilities\u2014Regulated Electric": 48,
    "Utilities\u2014Renewable": 49
  }
}